susepubliccloudinfo-1.4.0.data/scripts/pint
susepubliccloudinfoclient/__init__.py
susepubliccloudinfoclient/infoserverrequests.py
susepubliccloudinfoclient/version.py
susepubliccloudinfo-1.4.0.dist-info/LICENSE
susepubliccloudinfo-1.4.0.dist-info/METADATA
susepubliccloudinfo-1.4.0.dist-info/WHEEL
susepubliccloudinfo-1.4.0.dist-info/top_level.txt
susepubliccloudinfo-1.4.0.dist-info/RECORD
