Metadata-Version: 2.1
Name: susepubliccloudinfo
Version: 1.4.0
Summary: Command-line tool to access SUSE Public Cloud Information Service
Home-page: https://github.com/SUSE-Enceladus/public-cloud-info-client
Author: SUSE Public Cloud Team
Author-email: public-cloud-dev@susecloud.net
License: GPL-3.0+
Platform: UNKNOWN
Classifier: Development Status :: 5 - Production/Stable
Classifier: Intended Audience :: Developers
Classifier: Natural Language :: English
Classifier: License :: OSI Approved :: GNU General Public License v3 or later (GPLv3+)
Classifier: Programming Language :: Python
Classifier: Programming Language :: Python :: 3
Classifier: Programming Language :: Python :: 3.4
Classifier: Programming Language :: Python :: 3.5
Classifier: Programming Language :: Python :: 3.6
Classifier: Programming Language :: Python :: 3.7
Classifier: Programming Language :: Python :: Implementation :: CPython
Classifier: Programming Language :: Python :: Implementation :: PyPy
License-File: LICENSE
Requires-Dist: docopt
Requires-Dist: lxml
Requires-Dist: requests
Provides-Extra: dev
Requires-Dist: bumpversion ; extra == 'dev'
Requires-Dist: coverage ; extra == 'dev'
Requires-Dist: pycodestyle ; extra == 'dev'
Requires-Dist: nose ; extra == 'dev'
